mar_ps/__init__.py
mar_ps-0.1.1.dist-info/LICENSE
mar_ps-0.1.1.dist-info/METADATA
mar_ps-0.1.1.dist-info/WHEEL
mar_ps-0.1.1.dist-info/top_level.txt
mar_ps-0.1.1.dist-info/RECORD
