Metadata-Version: 2.1
Name: mar-ps
Version: 0.1.1
Summary: Multi-Agent Reasoning Problem Solver
Author-email: Hudson Gouge <hudson.gouge@icloud.com>
Project-URL: Homepage, https://github.com/hg0428/Mar-PS
Project-URL: Issues, https://github.com/hg0428/Mar-PS/issues
Classifier: Programming Language :: Python :: 3
Classifier: License :: OSI Approved :: MIT License
Classifier: Operating System :: OS Independent
Requires-Python: >=3.8
License-File: LICENSE
